groundwork_sphinx_theme/__init__.py
groundwork_sphinx_theme/flask_theme_support.py
groundwork_sphinx_theme/theme.conf
groundwork_sphinx_theme/static/groundwork.css_t
groundwork_sphinx_theme/static/gw_logo.png
groundwork_sphinx_theme/static/small_groundwork.css
groundwork_sphinx_theme/templates/contribute.html
groundwork_sphinx_theme/templates/layout.html
groundwork_sphinx_theme/templates/relations.html
groundwork_sphinx_theme/templates/searchbox.html
groundwork_sphinx_theme-1.1.1.dist-info/LICENSE
groundwork_sphinx_theme-1.1.1.dist-info/METADATA
groundwork_sphinx_theme-1.1.1.dist-info/WHEEL
groundwork_sphinx_theme-1.1.1.dist-info/entry_points.txt
groundwork_sphinx_theme-1.1.1.dist-info/top_level.txt
groundwork_sphinx_theme-1.1.1.dist-info/RECORD
