Metadata-Version: 1.1
Name: groundwork-sphinx-theme
Version: 1.1.1
Summary: Sphinx theme for groundwork projects (Based on flask_theme)
Home-page: https://github.com/useblocks/groundwork-sphinx-theme
Author: team useblocks
Author-email: info@useblocks.com
License: MIT
Platform: any
Classifier: Development Status :: 4 - Beta
Classifier: Environment :: Console
Classifier: Intended Audience :: Developers
Classifier: License :: OSI Approved :: MIT License
Classifier: Operating System :: OS Independent
Classifier: Programming Language :: Python
Classifier: Programming Language :: Python :: 3
Classifier: Programming Language :: Python :: 3.4
Classifier: Programming Language :: Python :: 3.5
